Metadata-Version: 2.1
Name: odoo14-addon-web_select_all_companies
Version: 14.0.1.0.1.dev2
Summary: Allows you to select all companies in one click.
Home-page: https://github.com/OCA/web
Author: Camptocamp, Odoo Community Association (OCA)
Author-email: support@odoo-community.org
License: LGPL-3
Classifier: Programming Language :: Python
Classifier: Framework :: Odoo
Classifier: Framework :: Odoo :: 14.0
Classifier: License :: OSI Approved :: GNU Lesser General Public License v3 (LGPLv3)
Requires-Python: >=3.6
Requires-Dist: odoo<14.1dev,>=14.0a
